sniffio/__init__.py
sniffio/_impl.py
sniffio/_version.py
sniffio/_tests/__init__.py
sniffio/_tests/test_sniffio.py
sniffio-1.1.0.dist-info/METADATA
sniffio-1.1.0.dist-info/RECORD
sniffio-1.1.0.dist-info/WHEEL
sniffio-1.1.0.dist-info/top_level.txt
