Metadata-Version: 1.2
Name: sniffio
Version: 1.1.0
Summary: Sniff out which async library your code is running under
Home-page: https://github.com/python-trio/sniffio
Author: Nathaniel J. Smith
Author-email: njs@pobox.com
License: MIT -or- Apache License 2.0
Keywords: async,trio,asyncio
Platform: UNKNOWN
Classifier: License :: OSI Approved :: MIT License
Classifier: License :: OSI Approved :: Apache Software License
Classifier: Framework :: Trio
Classifier: Framework :: AsyncIO
Classifier: Operating System :: POSIX :: Linux
Classifier: Operating System :: MacOS :: MacOS X
Classifier: Operating System :: Microsoft :: Windows
Classifier: Programming Language :: Python :: 3 :: Only
Classifier: Programming Language :: Python :: Implementation :: CPython
Classifier: Programming Language :: Python :: Implementation :: PyPy
Classifier: Intended Audience :: Developers
Classifier: Development Status :: 5 - Production/Stable
Requires-Python: >=3.5
